<?xml version="1.0" encoding="utf-8"?>
<odoo>
  <data>
    <record id="view_education_session_form" model="ir.ui.view">
      <field name="name">view.education.session.form</field>
      <field name="model">education.session</field>
      <field name="arch" type="xml">
        <form string="Education Session">
          <header>
            <field name="state" widget="statusbar"/>
          </header>
          <sheet>
            <group name="main">
              <field name="timetable_id"/>
            </group>
            <group name="data">
              <field name="date"/>
            </group>
            <group string="Session Ausences">
              <field name="ausence_ids" nolabel="1">
                <tree>
                  <field name="student_id" />
                  <field name="notes" />
                  <field name="supporting_document" />
                </tree>
              </field>
            </group>
          </sheet>
        </form>
      </field>
    </record>

    <record id="view_education_session_tree" model="ir.ui.view">
      <field name="name">view.education.session.tree</field>
      <field name="model">education.session</field>
      <field name="arch" type="xml">
        <tree string="Education Session">
          <field name="timetable_id"/>
          <field name="date"/>
          <field name="state"/>
        </tree>
      </field>
    </record>

    <record id="view_education_session_search" model="ir.ui.view">
      <field name="name">view.education.session.search</field>
      <field name="model">education.session</field>
      <field name="arch" type="xml">
        <search string="Education Session">
          <field name="date"/>
          <field name="timetable_id"/>
          <group string="Group By" name="groupby">
            <filter string="State" context="{'group_by': 'state'}"/>
            <filter string="Timetable" context="{'group_by': 'timetable_id'}"/>
            <filter string="Date" context="{'group_by': 'date'}"/>
          </group>
        </search>
      </field>
    </record>

    <record id="education_session_action" model="ir.actions.act_window">
      <field name="name">Education Session</field>
      <field name="res_model">education.session</field>
      <field name="view_mode">tree,form</field>
      <field name="help" type="html">
        <p class="oe_view_nocontent_create">
          Click to create a new Education Session.
        </p>
      </field>
    </record>

    <record id="session_sequence" model="ir.sequence">
      <field name="name">Edcation Session Sequence</field>
      <field name="code">education.session</field>
      <field name="prefix">SES</field>
      <field name="padding">3</field>
    </record>

    <menuitem id="education_session_menu" parent="education.education_assistance_root" action="education_session_action" sequence="20"/>

  </data>
</odoo>
